cloud_init_server/config_generator.py
cloud_init_server/create_app.py
cloud_init_server/exceptions.py
cloud_init_server/main.py
cloud_init_server/response.py
cloud_init_server/utils.py
cloud_init_server-0.1.0.dist-info/LICENSE
cloud_init_server-0.1.0.dist-info/WHEEL
cloud_init_server-0.1.0.dist-info/METADATA
cloud_init_server-0.1.0.dist-info/RECORD
